odoo/addons/hr_calendar_rest_time/README.rst
odoo/addons/hr_calendar_rest_time/__init__.py
odoo/addons/hr_calendar_rest_time/__manifest__.py
odoo/addons/hr_calendar_rest_time/i18n/hr_calendar_rest_time.pot
odoo/addons/hr_calendar_rest_time/migrations/12.0.1.0.0/post-migration.py
odoo/addons/hr_calendar_rest_time/models/__init__.py
odoo/addons/hr_calendar_rest_time/models/resource_calendar.py
odoo/addons/hr_calendar_rest_time/models/resource_calendar_attendance.py
odoo/addons/hr_calendar_rest_time/models/resource_mixin.py
odoo/addons/hr_calendar_rest_time/readme/CONTRIBUTORS.rst
odoo/addons/hr_calendar_rest_time/readme/DESCRIPTION.rst
odoo/addons/hr_calendar_rest_time/readme/HISTORY.rst
odoo/addons/hr_calendar_rest_time/readme/USAGE.rst
odoo/addons/hr_calendar_rest_time/static/description/icon.png
odoo/addons/hr_calendar_rest_time/static/description/index.html
odoo/addons/hr_calendar_rest_time/tests/__init__.py
odoo/addons/hr_calendar_rest_time/tests/test_hr_calendar_rest_time.py
odoo/addons/hr_calendar_rest_time/views/resource_calendar_attendance.xml
odoo12_addon_hr_calendar_rest_time-12.0.1.0.1.dist-info/METADATA
odoo12_addon_hr_calendar_rest_time-12.0.1.0.1.dist-info/WHEEL
odoo12_addon_hr_calendar_rest_time-12.0.1.0.1.dist-info/top_level.txt
odoo12_addon_hr_calendar_rest_time-12.0.1.0.1.dist-info/RECORD
